saygeek/__init__.py
saygeek/__main__.py
saygeek/saygeek.py
saygeek/resources/saygeek.db
saygeek-1.1.1.dist-info/LICENSE
saygeek-1.1.1.dist-info/METADATA
saygeek-1.1.1.dist-info/WHEEL
saygeek-1.1.1.dist-info/entry_points.txt
saygeek-1.1.1.dist-info/top_level.txt
saygeek-1.1.1.dist-info/RECORD
