Metadata-Version: 2.1
Name: saygeek
Version: 1.1.1
Summary: ALMA historical phrase generator
Home-page: https://github.com/bandaangosta/saygeek
Author: Jose L. Ortiz
Author-email: jlortiz@uc.cl
License: MIT
Platform: UNKNOWN
Classifier: Programming Language :: Python :: 3
Classifier: License :: OSI Approved :: MIT License
Classifier: Operating System :: OS Independent
Requires-Dist: click (==7.1.2)
Requires-Dist: typer (==0.3.2)
